MANIFEST.in
README.md
quicktest.py
settings_test.py
setup.py
django_facebook_pages_statistic.egg-info/PKG-INFO
django_facebook_pages_statistic.egg-info/SOURCES.txt
django_facebook_pages_statistic.egg-info/dependency_links.txt
django_facebook_pages_statistic.egg-info/not-zip-safe
django_facebook_pages_statistic.egg-info/requires.txt
django_facebook_pages_statistic.egg-info/top_level.txt
facebook_pages_statistic/__init__.py
facebook_pages_statistic/__init__.pyc
facebook_pages_statistic/admin.py
facebook_pages_statistic/admin.pyc
facebook_pages_statistic/factories.py
facebook_pages_statistic/factories.pyc
facebook_pages_statistic/models.py
facebook_pages_statistic/models.pyc
facebook_pages_statistic/signals.py
facebook_pages_statistic/signals.pyc
facebook_pages_statistic/tests.py
facebook_pages_statistic/tests.pyc
facebook_pages_statistic/migrations/0001_initial.py
facebook_pages_statistic/migrations/0001_initial.pyc
facebook_pages_statistic/migrations/__init__.py
facebook_pages_statistic/migrations/__init__.pyc