Metadata-Version: 1.1
Name: django-facebook-pages-statistic
Version: 0.6.0
Summary: Application for storing Facebook Pages statistic for different timesnaps
Home-page: https://github.com/ramusus/django-facebook-pages-statistic
Author: ramusus
Author-email: ramusus@gmail.com
License: BSD
Download-URL: http://pypi.python.org/pypi/django-facebook-pages-statistic
Platform: UNKNOWN
Classifier: Development Status :: 4 - Beta
Classifier: Environment :: Web Environment
Classifier: Intended Audience :: Developers
Classifier: License :: OSI Approved :: BSD License
Classifier: Operating System :: OS Independent
Classifier: Programming Language :: Python
Classifier: Topic :: Software Development :: Libraries :: Python Modules
